metastreamlit/__init__.py
metastreamlit/utils.py
metastreamlit/version.py
metastreamlit/audio_input/__init__.py
metastreamlit/audio_input/build/asset-manifest.json
metastreamlit/audio_input/build/index.html
metastreamlit/audio_input/build/precache-manifest.c831e00cbd4fd66a56ab656517bbf58e.js
metastreamlit/audio_input/build/service-worker.js
metastreamlit/audio_input/build/static/css/2.68a81a89.chunk.css
metastreamlit/audio_input/build/static/css/2.68a81a89.chunk.css.map
metastreamlit/audio_input/build/static/js/2.e7110a86.chunk.js
metastreamlit/audio_input/build/static/js/2.e7110a86.chunk.js.LICENSE.txt
metastreamlit/audio_input/build/static/js/2.e7110a86.chunk.js.map
metastreamlit/audio_input/build/static/js/main.ddccec24.chunk.js
metastreamlit/audio_input/build/static/js/main.ddccec24.chunk.js.map
metastreamlit/audio_input/build/static/js/runtime-main.11ec9aca.js
metastreamlit/audio_input/build/static/js/runtime-main.11ec9aca.js.map
metastreamlit/audio_input/build/static/media/ico_recording.bc7d967a.svg
metastreamlit/image_crop/__init__.py
metastreamlit/image_crop/build/asset-manifest.json
metastreamlit/image_crop/build/index.html
metastreamlit/image_crop/build/precache-manifest.ee299a3610f7c3bb0ac057e75cd84527.js
metastreamlit/image_crop/build/service-worker.js
metastreamlit/image_crop/build/static/css/2.a7708dfc.chunk.css
metastreamlit/image_crop/build/static/css/2.a7708dfc.chunk.css.map
metastreamlit/image_crop/build/static/js/2.485d8b29.chunk.js
metastreamlit/image_crop/build/static/js/2.485d8b29.chunk.js.LICENSE.txt
metastreamlit/image_crop/build/static/js/2.485d8b29.chunk.js.map
metastreamlit/image_crop/build/static/js/main.5d5f82a4.chunk.js
metastreamlit/image_crop/build/static/js/main.5d5f82a4.chunk.js.LICENSE.txt
metastreamlit/image_crop/build/static/js/main.5d5f82a4.chunk.js.map
metastreamlit/image_crop/build/static/js/runtime-main.11ec9aca.js
metastreamlit/image_crop/build/static/js/runtime-main.11ec9aca.js.map
metastreamlit/image_input/__init__.py
metastreamlit-0.4.7.dist-info/LICENSE
metastreamlit-0.4.7.dist-info/METADATA
metastreamlit-0.4.7.dist-info/WHEEL
metastreamlit-0.4.7.dist-info/top_level.txt
metastreamlit-0.4.7.dist-info/RECORD
