Metadata-Version: 2.1
Name: metastreamlit
Version: 0.4.7
Summary: Helper library for creating ML demos in streamlit
Home-page: UNKNOWN
Author: Daniel Haziza
Author-email: 
License: UNKNOWN
Platform: UNKNOWN
Requires-Python: >=3.6
License-File: LICENSE
Requires-Dist: streamlit (>=1.9)
Requires-Dist: matplotlib
